NLEParser/__init__.py
NLEParser/parser.py
nleparser-0.2.7.dist-info/METADATA
nleparser-0.2.7.dist-info/WHEEL
nleparser-0.2.7.dist-info/top_level.txt
nleparser-0.2.7.dist-info/RECORD
