Metadata-Version: 2.4
Name: NLEParser
Version: 0.2.7
Summary: A Natural Language processing parser for Zork-style games
Author: NatanLang
Author-email: natanrcorreiatr@gmail.com
Classifier: Programming Language :: Python :: 3
Classifier: License :: OSI Approved :: MIT License
Classifier: Operating System :: OS Independent
Requires-Python: >=3.13
Dynamic: author
Dynamic: author-email
Dynamic: classifier
Dynamic: description
Dynamic: description-content-type
Dynamic: requires-python
Dynamic: summary
